cuke/__init__.py
cuke/errors.py
cuke/types.py
cuke/util.py
cuke-0.2.0.dist-info/METADATA
cuke-0.2.0.dist-info/WHEEL
cuke-0.2.0.dist-info/RECORD
